sinapsis_supervision/__init__.py
sinapsis_supervision/templates/__init__.py
sinapsis_supervision/templates/byte_track.py
sinapsis_supervision-0.1.4.dist-info/licenses/LICENSE
sinapsis_supervision-0.1.4.dist-info/METADATA
sinapsis_supervision-0.1.4.dist-info/WHEEL
sinapsis_supervision-0.1.4.dist-info/top_level.txt
sinapsis_supervision-0.1.4.dist-info/RECORD
