Metadata-Version: 2.4
Name: sinapsis-supervision
Version: 0.1.4
Summary:  Templates for multi-object tracking using the ByteTrack algorithm
Author-email: SinapsisAI <dev@sinapsis.tech>
Project-URL: Homepage, https://sinapsis.tech
Project-URL: Documentation, https://docs.sinapsis.tech/docs
Project-URL: Tutorials, https://docs.sinapsis.tech/tutorials
Project-URL: Repository, https://github.com/Sinapsis-AI/sinapsis-trackers.git
Requires-Python: >=3.10
License-File: LICENSE
Requires-Dist: sinapsis>=0.2.2
Requires-Dist: sinapsis-data-visualization[visualization-matplotlib]>=0.1.0
Requires-Dist: supervision>=0.22.0
Provides-Extra: all
Requires-Dist: sinapsis-supervision[gradio,sinapsis-data-readers,sinapsis-data-writers,sinapsis-dfine,sinapsis-ultralytics]; extra == "all"
Provides-Extra: sinapsis-ultralytics
Requires-Dist: sinapsis-ultralytics>=0.1.1; extra == "sinapsis-ultralytics"
Provides-Extra: sinapsis-dfine
Requires-Dist: sinapsis-dfine[training]>=0.1.1; extra == "sinapsis-dfine"
Provides-Extra: sinapsis-data-readers
Requires-Dist: sinapsis-data-readers[opencv]>=0.1.2; extra == "sinapsis-data-readers"
Provides-Extra: sinapsis-data-writers
Requires-Dist: sinapsis-data-writers>=0.1.1; extra == "sinapsis-data-writers"
Provides-Extra: sinapsis-define
Requires-Dist: sinapsis-dfine[training]>=0.1.3; extra == "sinapsis-define"
Dynamic: license-file
